yarxiv_mcp/__init__.py
yarxiv_mcp/__main__.py
yarxiv_mcp/server.py
yarxiv_mcp/tools/arxiv_search.py
yarxiv_mcp-0.0.1.dist-info/METADATA
yarxiv_mcp-0.0.1.dist-info/WHEEL
yarxiv_mcp-0.0.1.dist-info/entry_points.txt
yarxiv_mcp-0.0.1.dist-info/top_level.txt
yarxiv_mcp-0.0.1.dist-info/RECORD
